COPYING
HISTORY
LICENSE
MANIFEST.in
README
README.rst
setup.cfg
setup.py
./src/asterix/AsterixData.cpp
./src/asterix/AsterixDefinition.cpp
./src/asterix/Category.cpp
./src/asterix/DataBlock.cpp
./src/asterix/DataItem.cpp
./src/asterix/DataItemBits.cpp
./src/asterix/DataItemDescription.cpp
./src/asterix/DataItemFormat.cpp
./src/asterix/DataItemFormatBDS.cpp
./src/asterix/DataItemFormatCompound.cpp
./src/asterix/DataItemFormatExplicit.cpp
./src/asterix/DataItemFormatFixed.cpp
./src/asterix/DataItemFormatRepetitive.cpp
./src/asterix/DataItemFormatVariable.cpp
./src/asterix/DataRecord.cpp
./src/asterix/InputParser.cpp
./src/asterix/Tracer.cpp
./src/asterix/UAP.cpp
./src/asterix/UAPItem.cpp
./src/asterix/Utils.cpp
./src/asterix/XMLParser.cpp
./src/python/asterix.c
./src/python/python_parser.cpp
./src/python/python_wrapper.c
asterix/__init__.py
asterix/version.py
asterix/config/asterix.dtd
asterix/config/asterix_bds.xml
asterix/config/asterix_cat001_1_2.xml
asterix/config/asterix_cat002_1_0.xml
asterix/config/asterix_cat004_1_13.xml
asterix/config/asterix_cat008_1_0.xml
asterix/config/asterix_cat010_1_1.xml
asterix/config/asterix_cat011_1_2.xml
asterix/config/asterix_cat015_1_2.xml
asterix/config/asterix_cat019_1_3.xml
asterix/config/asterix_cat020_1_10.xml
asterix/config/asterix_cat021_2_6.xml
asterix/config/asterix_cat023_1_3.xml
asterix/config/asterix_cat025_1_5.xml
asterix/config/asterix_cat030_6_2.xml
asterix/config/asterix_cat031_6_2.xml
asterix/config/asterix_cat032_7_0.xml
asterix/config/asterix_cat034_1_27.xml
asterix/config/asterix_cat048_1_21.xml
asterix/config/asterix_cat062_1_18.xml
asterix/config/asterix_cat063_1_3.xml
asterix/config/asterix_cat065_1_3.xml
asterix/config/asterix_cat205_1_0.xml
asterix/config/asterix_cat240_1_3.xml
asterix/config/asterix_cat247_1_2.xml
asterix/config/asterix_cat252_7_0.xml
asterix/examples/__init__.py
asterix/examples/multicast_receive.py
asterix/examples/multicast_send_receive.py
asterix/examples/read_final_file.py
asterix_decoder.egg-info/PKG-INFO
asterix_decoder.egg-info/SOURCES.txt
asterix_decoder.egg-info/dependency_links.txt
asterix_decoder.egg-info/not-zip-safe
asterix_decoder.egg-info/top_level.txt
